preprocess_ai/__init__.py
preprocess_ai/DataPreparation/DataPartitioner.py
preprocess_ai/DataPreparation/__init__.py
preprocess_ai/DataPreparation/DataCleaner/__init__.py
preprocess_ai/DataPreparation/DataCleaner/dataCleaner.py
preprocess_ai/DataPreparation/DataCleaner/dataTransformer.py
preprocess_ai/DataPreparation/DataCleaner/duplicationHandler.py
preprocess_ai/DataPreparation/DataCleaner/outlierHandler.py
preprocess_ai/DataPreparation/DataReduction/__init__.py
preprocess_ai/DataPreparation/DataReduction/dimensionalityReducer.py
preprocess_ai/DataPreparation/DataReduction/featureSelector.py
preprocess_ai/DataPreparation/DataTransformation/__init__.py
preprocess_ai/DataPreparation/DataTransformation/categoricalEncoder.py
preprocess_ai/DataPreparation/DataTransformation/featureEngineer.py
preprocess_ai/DataPreparation/DataTransformation/scaler.py
preprocess_ai/tests/__init__.py
preprocess_ai/tests/dataPartitioner_unit_test.py
preprocess_ai/tests/dataCleaning_integration_test/__init__.py
preprocess_ai/tests/dataCleaning_integration_test/remove_empty_data_and_duplicates_test.py
preprocess_ai/tests/dataCleaning_unit_test/__init__.py
preprocess_ai/tests/dataCleaning_unit_test/dataCleaner_transformer_test.py
preprocess_ai/tests/dataCleaning_unit_test/data_cleaner_test.py
preprocess_ai/tests/dataCleaning_unit_test/duplication_handler_test.py
preprocess_ai/tests/dataCleaning_unit_test/outlier_dectector_test.py
preprocess_ai/tests/dataReduction_unit_test/__init__.py
preprocess_ai/tests/dataReduction_unit_test/dimensionalityReducer_test.py
preprocess_ai/tests/dataReduction_unit_test/featureSelector_test.py
preprocess_ai/tests/dataTransformer_unit_test/__init__.py
preprocess_ai/tests/dataTransformer_unit_test/categoricalEncoder_test.py
preprocess_ai/tests/dataTransformer_unit_test/featureEngineer_test.py
preprocess_ai/tests/dataTransformer_unit_test/scaler_test.py
preprocess_ai-0.2.20.dist-info/METADATA
preprocess_ai-0.2.20.dist-info/WHEEL
preprocess_ai-0.2.20.dist-info/top_level.txt
preprocess_ai-0.2.20.dist-info/RECORD
